MANIFEST.in
fastentrypoints.py
remodep.py
setup.py
remodep.egg-info/PKG-INFO
remodep.egg-info/SOURCES.txt
remodep.egg-info/dependency_links.txt
remodep.egg-info/entry_points.txt
remodep.egg-info/requires.txt
remodep.egg-info/top_level.txt