Metadata-Version: 1.1
Name: remodep
Version: 1.0.0
Summary: List reverse kernel module dependencies
Home-page: https://github.com/thusoy/remodep
Author: Tarjei Husøy
Author-email: git@thusoy.com
License: UNKNOWN
Platform: UNKNOWN
Classifier: Development Status :: 5 - Production/Stable
Classifier: Operating System :: POSIX :: Linux
Classifier: Intended Audience :: System Administrators
Classifier: License :: OSI Approved :: MIT License
Classifier: Programming Language :: Python :: 2.6
Classifier: Programming Language :: Python :: 2.7
Classifier: Programming Language :: Python :: 3.3
Classifier: Programming Language :: Python :: 3.4
Classifier: Programming Language :: Python :: 3.5
